{
    "nixpkgs": {
        "branch": "nixos-unstable",
        "description": "Nix Packages collection",
        "homepage": null,
        "owner": "NixOS",
        "repo": "nixpkgs",
        "rev": "e6eae2ee2110f3d31110d5c222cd395303343b08",
        "sha256": "1mqwcpjyq690m9m52njw0dr9baw715s4j9sh7s8nq5wf8psm6w98",
        "type": "tarball",
        "url": "https://github.com/NixOS/nixpkgs/archive/e6eae2ee2110f3d31110d5c222cd395303343b08.tar.gz",
        "url_template": "https://github.com/<owner>/<repo>/archive/<rev>.tar.gz"
    }
}
